cerberus/__init__.py
cerberus/__main__.py
cerberus/api.py
cerberus/cerberus.py
cerberus/config_parser.py
cerberus/exceptions.py
cerberus/__pycache__/__init__.cpython-38.pyc
cerberus/__pycache__/config_parser.cpython-38.pyc
cerberus_controller-0.1.8.data/data/etc/cerberus/topology.json
cerberus_controller-0.1.8.data/data/etc/cerberus/umbrella.json
cerberusctl/__init__.py
cerberusctl/__main__.py
cerberusctl/api.py
cerberusctl/cerberus.py
cerberusctl/config_parser.py
cerberusctl/exceptions.py
cerberus_controller-0.1.8.dist-info/AUTHORS
cerberus_controller-0.1.8.dist-info/LICENSE
cerberus_controller-0.1.8.dist-info/METADATA
cerberus_controller-0.1.8.dist-info/WHEEL
cerberus_controller-0.1.8.dist-info/entry_points.txt
cerberus_controller-0.1.8.dist-info/pbr.json
cerberus_controller-0.1.8.dist-info/top_level.txt
cerberus_controller-0.1.8.dist-info/RECORD
