Metadata-Version: 2.1
Name: cerberus-controller
Version: 0.1.8
Summary: Proactive Openflow Controller for layer 2 networks
Home-page: https://github.com/Holist-IX/cerberus
Author: Christoff Visser
Author-email: christoff@iij.ad.jp
License: UNKNOWN
Keywords: OpenFLow,SDN,P4
Platform: any
Requires-Python: >=3.8
Requires-Dist: eventlet (==0.30.2)
Requires-Dist: ryu (>=4.34)
